mbproto/__init__.py
mbproto/mb_protocol_answers_pb2.py
mbproto/mb_protocol_commands_pb2.py
mbproto/mb_protocol_enums_pb2.py
mbproto/mb_protocol_iface.py
mbproto/mb_protocol_pb2.py
mbproto-1.0.2.dist-info/METADATA
mbproto-1.0.2.dist-info/WHEEL
mbproto-1.0.2.dist-info/licenses/LICENSE
mbproto-1.0.2.dist-info/RECORD
