Metadata-Version: 2.4
Name: mbproto
Version: 1.0.2
Summary: mbprotocol
License: Apache-2.0
License-File: LICENSE
Author: Jan Kowalewski
Author-email: <jkowalewski@cthings.co>
Maintainer: Jan Kowalewski
Maintainer-email: <jkowalewski@cthings.co>
Requires-Python: >=3.11
Classifier: License :: OSI Approved :: Apache Software License
Classifier: Programming Language :: Python :: 3
Classifier: Programming Language :: Python :: 3.11
Classifier: Programming Language :: Python :: 3.12
Classifier: Programming Language :: Python :: 3.13
Classifier: Programming Language :: Python :: 3.14
Requires-Dist: crccheck (>=1.3.0)
Requires-Dist: cthingsco-pymodbus[serial] (>=3.8.3)
Requires-Dist: protobuf (>=6.31.1)
